textadventure/__init__.py
textadventure/input.py
textadventure/menu.py
textadventure/output.py
textadventure/timing.py
textadventure-0.0.9.dist-info/METADATA
textadventure-0.0.9.dist-info/WHEEL
textadventure-0.0.9.dist-info/licenses/LICENSE.md
textadventure-0.0.9.dist-info/RECORD
