Metadata-Version: 2.3
Name: textadventure
Version: 0.0.9
Summary: A small package to make creating your own text adventure games easy!
Project-URL: Homepage, https://github.com/Matt-DESTROYER/textadventure
Project-URL: Issues, https://github.com/Matt-DESTROYER/textadventure/issues
Author-email: Matthew James <mattdestroyerpro@gmail.com>
License-File: LICENSE.md
Classifier: Operating System :: OS Independent
Classifier: Programming Language :: Python :: 3
Requires-Python: >=3.8
Requires-Dist: getkey
